goesvideo/__init__.py
goesvideo/exceptions.py
goesvideo/goesvideo.py
goesvideo/addons/__init__.py
goesvideo/addons/overlays.py
goesvideo/addons/sceneeditor.py
goesvideo/demos/create_video_goes_west_demo.py
goesvideo/demos/scene_edit_demo.py
goesvideo/etc/abibands.yaml
goesvideo/tests/__init__.py
goesvideo/tests/test_animating.py
goesvideo/tests/test_compositing.py
goesvideo/tests/test_download.py
goesvideo/tests/test_generic_overlays.py
goesvideo/tests/test_preview.py
goesvideo/tests/test_scene_editor.py
goesvideo/tests/test_video_editing.py
goesvideo/tests/treegenerator.py
goesvideo/tests/Fonts/Roboto-Regular.ttf
goesvideo/tests/Test Images/2024-10-08 17_58_54 UTC.png
goesvideo/tests/Test Images/2024-10-08 17_58_54 UTC.tif
goesvideo/tests/Test Images/2024-10-08 18_03_54 UTC.png
goesvideo/tests/Test Images/2024-10-08 18_03_54 UTC.tif
goesvideo/tests/Test Images/2024-10-08 18_13_54 UTC.png
goesvideo/tests/Test Images/2024-10-08 18_13_54 UTC.tif
goesvideo/tests/Test Images/2024-10-08 18_23_54 UTC.png
goesvideo/tests/Test Images/2024-10-08 18_23_54 UTC.tif
goesvideo/tests/Test Images/2024-10-08 18_33_54 UTC.png
goesvideo/tests/Test Images/2024-10-08 18_33_54 UTC.tif
goesvideo/tests/Test Images/2024-10-08 18_43_54 UTC.png
goesvideo/tests/Test Images/2024-10-08 18_43_54 UTC.tif
goesvideo/tests/Test Images/2024-10-08 18_53_54 UTC.png
goesvideo/tests/Test Images/2024-10-08 18_53_54 UTC.tif
goesvideo/tests/Test Images/2024-10-08 18_58_54 UTC.png
goesvideo/tests/Test Images/2024-10-08 18_58_54 UTC.tif
goesvideo/tests/Test Images/metadata.json
goesvideo/tests/Test Images/timestamps.csv
goesvideo/tests/Test Images/timestamps_overlay.csv
goesvideo/tests/Test NC Files/OR_ABI-L2-CMIPF-M6C01_G16_s20231411110208_e20231411119516_c20231411119596.nc
goesvideo/tests/Test NC Files/OR_ABI-L2-CMIPF-M6C02_G16_s20231411110208_e20231411119516_c20231411119590.nc
goesvideo/tests/Test NC Files/OR_ABI-L2-CMIPF-M6C03_G16_s20231411110208_e20231411119516_c20231411119596.nc
goesvideo-2024.11.5.dist-info/LICENSE
goesvideo-2024.11.5.dist-info/METADATA
goesvideo-2024.11.5.dist-info/WHEEL
goesvideo-2024.11.5.dist-info/top_level.txt
goesvideo-2024.11.5.dist-info/RECORD
