Metadata-Version: 2.1
Name: goesvideo
Version: 2024.11.5
Summary: Package to streamline operations with GOES satellite imagery
Author: Justin Holland
Project-URL: Repository, https://github.com/qubitqualia/goesvideo.git
Classifier: Programming Language :: Python :: 3
Classifier: Programming Language :: Python :: 3.10
Classifier: Programming Language :: Python :: 3.11
Classifier: Programming Language :: Python :: 3.12
Classifier: License :: OSI Approved :: MIT License
Classifier: Operating System :: OS Independent
Requires-Python: >=3.10
License-File: LICENSE
Requires-Dist: boto3 >=1.34.140
Requires-Dist: botocore >=1.34.140
Requires-Dist: colorama >=0.4.6
Requires-Dist: matplotlib >=3.8.4
Requires-Dist: moviepy >=1.0.3
Requires-Dist: netCDF4 >=1.6.2
Requires-Dist: Pillow >=10.1.0
Requires-Dist: pyspectral >=0.12.5
Requires-Dist: pytz >=2024.1
Requires-Dist: PyYAML >=6.0.1
Requires-Dist: rasterio >=1.3.10
Requires-Dist: satpy >=0.49.0
Requires-Dist: tqdm >=4.66.4
Requires-Dist: numpy >=1.26.4 ; python_version > "3.9"
Requires-Dist: urllib3 >=2.0.2 ; python_version > "3.9"
